Lab_Final.srcs/sources_1/new/adder_logic.v

module adder_logic(
input A,
input B,
input C,

output Y,
output Cout
);
// Simplified: A ^ B ^ C
// Kmap derivation:  (~A & ~B & C) | (~A & B & ~C) | (A & B & C) | (A & ~B & ~C)
assign Y = A ^ B ^ C;
// Simplified: (A | B) & C
// Kmap derivation: (B & C) | (A & B) | (A & C) 
assign Cout = (B & C) | (A & B) | (A & C);


endmodule

Lab_Final.srcs/sources_1/new/adder_calc.v
module adder_calc(
    input [3:0] A,
    input [3:0] B,
    output [3:0] Y
);

    

    wire [3:0] second_carry; 
    
    adder_logic lsb(
        .A(A[0]), 
        .B(B[0]), 
        .Y(Y[0]), 
        .C(0), 
        .Cout(second_carry[0]) 
    );
   
    adder_logic bit1(
        .A(A[1]), 
        .B(B[1]), 
        .Y(Y[1]), 
        .C(second_carry[0]), 
        .Cout(second_carry[1]) 
    );
    

    adder_logic bit2(
        .A(A[2]), 
        .B(B[2]), 
        .Y(Y[2]), 
        .C(second_carry[1]), 
        .Cout(second_carry[2])
        // bit of second addition
    
    );
    
    adder_logic msb(
        .A(A[3]),
        .B(B[3]),
        .Y(Y[3]),
        .C(second_carry[2]),
        .Cout(second_carry[3])
        // no carry out!
     );
endmodule

math_block.v
module math_block(
    input [3:0] Aval,
    input [3:0] Bval,
    output [3:0] AplusB,
    output [3:0] AminusB
);

wire [3:0] Bminus; //holds two value of B (-B)

    adder_calc twosconversion (
    .A(~Bval [3:0]),
    .B(4'b0001), //adds the extra bit
    .Y(Bminus [3:0])
    );
    
    adder_calc Aplus(
        .A(Aval [3:0]),
        .B(Bval [3:0]),
        .Y(AplusB [3:0])
    );
    
    adder_calc Aminus(
        .A(Aval [3:0]),
        .B(Bminus [3:0]),
        .Y(AminusB [3:0])
    );
endmodule

seven_seg_decoder.v
module seven_seg_decoder(
    input [3:0] A,
    input [3:0] B,
    input [3:0] AplusB,
    input [3:0] AminusB,
    input [3:0] anode,
    output reg [6:0] segs
);

reg [3:0]selected_sig;

    always@(*) begin
        case(anode)
            4'b1110: selected_sig <= A;//R (A
            4'b1101: selected_sig <= B;//RC (B
            4'b1011: selected_sig <= AplusB;//LC (A+B)
            4'b0111: selected_sig <= AminusB;//L (A-B)
         endcase
     end
    // Decoder, provided free of charge!
    always @(*) begin
        case(selected_sig)
            //            GFEDCBA
            0: segs  = 7'b1000000;        
            1: segs  = 7'b1111001;        
            2: segs  = 7'b0100100;        
            3: segs  = 7'b0110000;        
            4: segs  = 7'b0011001;        
            5: segs  = 7'b0010010;        
            6: segs  = 7'b0000010;        
            7: segs  = 7'b1111000;        
            8: segs  = 7'b0000000;
            9: segs  = 7'b0010000;        
            10: segs = 7'b0001000;        
            11: segs = 7'b0000011;        
            12: segs = 7'b1000110;        
            13: segs = 7'b0100001;        
            14: segs = 7'b0000110;        
            15: segs = 7'b0001110;       
        endcase
    end

endmodule

Lab_Final.srcs/sources_1/new/DFF.v
`timescale 1ns / 1ps

module DFF(
    input Default,
    input D,
    input clk,
    input r,
    output reg Q,
    output NotQ
);
    assign NotQ = ~Q;
    
    initial begin
        Q <= Default;
    end

    always @(posedge clk, posedge r) begin
        if (r)begin
            Q <= Default;
            end      
        else begin
            Q <= D;
            end 
    end
endmodule

seven_seg_scanner.v
module seven_seg_scanner(
    input div_clock,
    input reset,
    output [3:0] anode
);
//// inverse one-hot encoding (nickname one-cold)
//wire [3:0] state;
//wire [3:0] next;

//    DFF msb_init( //high to low
//    .Default(1'b1),
//    .D(next[3]),
//    .clk(div_clock),
//    .r(reset),
//    .Q(state[3])
//);

//DFF bit_init(
//    .Default(1'b1),
//    .D(next[2]),
//    .clk(div_clock),
//    .r(reset),
//    .Q(state[2])
//);

//DFF bit_three_init(
//    .Default(1'b1),
//    .D(next[1]),
//    .clk(div_clock),
//    .r(reset),
//    .Q(state[1])
//);

//DFF lsb_init(
//    .Default(1'b0),
//    .D(next[0]),
//    .clk(div_clock),
//    .r(reset),
//    .Q(state[0])
//);
    

//    assign next[3] =  state[2]; 
//    assign next[2] = state[1];
//    assign next[1] = state[0];
//    assign next[0] = state[3];
    
//    assign anode ={state[3],state[2],state[1],state[0]};

//binary encoding

wire [1:0] bin_val;
wire [1:0] bin_state;
reg [3:0]anode_binary;

DFF msb_init( //high to low
    .Default(1'b1),
    .D(bin_val[1]),
    .clk(div_clock),
    .r(reset),
    .Q(bin_state[1])
);

DFF lsb_init( //high to low
    .Default(1'b1),
    .D(bin_val[0]),
    .clk(div_clock),
    .r(reset),
    .Q(bin_state[0])
);

    assign bin_val[1] =  bin_state[1] ^ bin_state[0]; 
    assign bin_val[0] = ~bin_state[0];
    
    always @(*)begin
        case(bin_val)
            2'b00: anode_binary <= 4'b1110;
            2'b01: anode_binary <= 4'b1101;
            2'b10: anode_binary <= 4'b1011;
            2'b11: anode_binary <= 4'b0111;
        endcase
    end
    
    assign anode = anode_binary;
endmodule

clock_div.v
module clock_div
#(
    parameter DIVIDE_BY = 17
)
(
    input clock,
    input reset,
    output div_clock
);

    genvar i;
    wire [16:0]notHold;
    wire [16:0]div_clock_hold;
    
    
    DFF initbase(
                .Default(1'b0),
                .D(notHold[0]),
                .clk(clock),
                .r(reset),
                .Q(div_clock_hold[0]),
                .NotQ(notHold[0])
            );
             
    generate
        for (i = 1; i < DIVIDE_BY; i = i + 1)begin //saves writing out DFF 17 times
        
            DFF init(
                .Default(1'b0),
                .D(notHold[i]),
                .clk(div_clock_hold[i - 1]),
                .r(reset),
                .Q(div_clock_hold[i]),
                .NotQ(notHold[i])
            );

        end
    endgenerate

    assign div_clock = div_clock_hold[DIVIDE_BY - 1]; //used param to make testing work correctly

endmodule

top.v
module top
#(
    parameter DIVIDE_BY = 17 // Use this when passing in to your clock div!
    // The test bench will set it appropriately for testing
)
(
    input [7:0] sw, // A and B
    input clk, // 100 MHz board clock
    input btnC, // Reset
    output [3:0] an, // 7seg anodes
    output [6:0] seg // 7seg segments
);

    // Instantiate the clock divider...
    wire clock_div_val;
    
    clock_div #(.DIVIDE_BY(DIVIDE_BY))clockinit( //# needed for testing changes
        .clock(clk),
        .reset(btnC),
        .div_clock(clock_div_val)
    );
    
    // ... wire it up to the scanner
    seven_seg_scanner scaninit(
        .div_clock(clock_div_val),
        .reset(btnC),
        .anode(an[3:0])
    );
    // ... wire the scanner to the decoder
    seven_seg_decoder decodeinit(
        .A(sw[3:0]),
        .B(sw[7:4]),
        .AplusB(Aplus[3:0]),
        .AminusB(Aminus[3:0]),
        .anode(an[3:0]),
        .segs(seg[6:0])
    );
    // Wire up the math block into the decoder
wire [3:0]Aplus;
wire[3:0]Aminus;

    math_block mathinit(
        .Aval(sw[3:0]),
        .Bval(sw[7:4]),
        .AplusB(Aplus[3:0]),
        .AminusB(Aminus[3:0])
    );

    // Do not forget to wire up resets!!

endmodule

test.v
`timescale 1ns/1ps

module test();

	reg [3:0] A, B;
    reg clk;
    reg btnC;
    wire [3:0] AminusB, AplusB;
    wire [3:0] an;
    wire [6:0] seg;
    wire [7:0] sw;
    integer i, j;

    // Might need to be .DIVIDE_BY(2) based
    // on your implementation
    top #(.DIVIDE_BY(1)) uut(
        .sw(sw),
        .clk(clk),
        .btnC(btnC),
        .an(an),
        .seg(seg)
    );

	assign sw = {B, A};
	assign AminusB = A - B;
	assign AplusB = A + B;

    task automatic advance_clock;
        begin
            #1 clk = ~clk;
            #1 clk = ~clk;
            #1 clk = ~clk;
            #1 clk = ~clk;
        end
    endtask
    
	function automatic [6:0] seg_encode(
		input [3:0] value
	);
		begin
			case(value)
				//                  GFEDCBA
				0:  seg_encode = 7'b1000000;
				1:  seg_encode = 7'b1111001;
				2:  seg_encode = 7'b0100100;
				3:  seg_encode = 7'b0110000;
				4:  seg_encode = 7'b0011001;
				5:  seg_encode = 7'b0010010;
				6:  seg_encode = 7'b0000010;
				7:  seg_encode = 7'b1111000;
				8:  seg_encode = 7'b0000000;
				9:  seg_encode = 7'b0010000;
				10: seg_encode = 7'b0001000; // A
				11: seg_encode = 7'b0000011; // B
				12: seg_encode = 7'b1000110; // C
				13: seg_encode = 7'b0100001; // D
				14: seg_encode = 7'b0000110; // E
				15: seg_encode = 7'b0001110; // F
				default: seg_encode = 7'b1000001; // U for unknown
			endcase
		end
	endfunction

    task automatic test_segs(
        input [7:0] expected_segR,
        input [7:0] expected_segRC,
        input [7:0] expected_segLC,
        input [7:0] expected_segL
    );
        begin
            if (seg !== expected_segR) begin
                $display("Test failed, segment R!");
                $display ("expected value = %b", expected_segR);//added by student
                $display ("actual value = %b", seg);//added by student
                $finish;
            end
            advance_clock();
            if (seg !== expected_segRC) begin
                $display("Test failed, segment RC!");
                $display ("expected value = %b", expected_segRC);//added by student
                $display ("actual value = %b", seg);//added by student
                $finish;
            end
            advance_clock();
            if (seg !== expected_segLC) begin
                $display("Test failed, segment LC!");
                $display ("expected value = %b", expected_segLC);//added by student
                $display ("actual value = %b", seg);//added by student
                $finish;
            end
            advance_clock();
            if (seg !== expected_segL) begin
                $display("Test failed, segment L!");
                $display ("expected value = %b", expected_segL);//added by student
                $display ("actual value = %b", seg);//added by student
                $finish;
            end
            advance_clock();
        end
    endtask

    initial begin
		$dumpvars(0, test);
		clk = 0;
		btnC = 1;
		#5;
		btnC = 0;
		

        for (i = 0; i < 16; i = i + 1) begin
            for (j = 0; j < 16; j = j + 1) begin
                A = i;
                B = j;
                #1;
                $display("Testing A = %0d (0x%0h), B = %0d (0x%0h)...", A, A, B, B);
                test_segs(seg_encode(A), seg_encode(B), seg_encode(A + B), seg_encode(A - B));
                $display("--Success");
            end
        end

		$display("All tests passed!");
		$finish;
	end



endmodule

Lab_Final.sim/sim_1/behav/xsim/dump.vcd
$date
   Thu May  1 15:41:53 2025
$end

$version
  2024.2.0
$end

$timescale
  1ps
$end

$scope module test $end
$var reg 4 ! A [3:0] $end
$var reg 4 " B [3:0] $end
$var reg 1 # clk $end
$var reg 1 $ btnC $end
$var wire 4 % AminusB [3:0] $end
$var wire 4 & AplusB [3:0] $end
$var wire 4 ' an [3:0] $end
$var wire 7 ( seg [6:0] $end
$var wire 8 ) sw [7:0] $end
$var integer 32 * i [31:0] $end
$var integer 32 + j [31:0] $end
$scope module uut $end
$var wire 8 ) sw [7:0] $end
$var wire 1 , clk $end
$var wire 1 - btnC $end
$var wire 4 ' an [3:0] $end
$var wire 7 ( seg [6:0] $end
$var wire 1 . clock_div_val $end
$var wire 4 / Aplus [3:0] $end
$var wire 4 0 Aminus [3:0] $end
$scope module clockinit $end
$var wire 1 , clock $end
$var wire 1 - reset $end
$var wire 1 . div_clock $end
$var wire 17 1 notHold [16:0] $end
$var wire 17 2 div_clock_hold [16:0] $end
$scope module initbase $end
$var wire 1 3 Default $end
$var wire 1 4 D $end
$var wire 1 , clk $end
$var wire 1 - r $end
$var reg 1 5 Q $end
$var wire 1 4 NotQ $end
$upscope $end
$upscope $end
$scope module scaninit $end
$var wire 1 . div_clock $end
$var wire 1 - reset $end
$var wire 4 ' anode [3:0] $end
$var wire 2 6 bin_val [1:0] $end
$var wire 2 7 bin_state [1:0] $end
$var reg 4 8 anode_binary [3:0] $end
$scope module msb_init $end
$var wire 1 9 Default $end
$var wire 1 : D $end
$var wire 1 . clk $end
$var wire 1 - r $end
$var reg 1 ; Q $end
$var wire 1 < NotQ $end
$upscope $end
$scope module lsb_init $end
$var wire 1 = Default $end
$var wire 1 > D $end
$var wire 1 . clk $end
$var wire 1 - r $end
$var reg 1 ? Q $end
$var wire 1 @ NotQ $end
$upscope $end
$upscope $end
$scope module decodeinit $end
$var wire 4 A A [3:0] $end
$var wire 4 B B [7:4] $end
$var wire 4 / AplusB [3:0] $end
$var wire 4 0 AminusB [3:0] $end
$var wire 4 ' anode [3:0] $end
$var reg 7 C segs [6:0] $end
$var reg 4 D selected_sig [3:0] $end
$upscope $end
$scope module mathinit $end
$var wire 4 A Aval [3:0] $end
$var wire 4 B Bval [7:4] $end
$var wire 4 / AplusB [3:0] $end
$var wire 4 0 AminusB [3:0] $end
$var wire 4 E Bminus [3:0] $end
$scope module twosconversion $end
$var wire 4 F A [3:0] $end
$var wire 4 G B [3:0] $end
$var wire 4 E Y [3:0] $end
$var wire 4 H second_carry [3:0] $end
$scope module lsb $end
$var wire 1 I A $end
$var wire 1 J B $end
$var wire 1 K C $end
$var wire 1 L Y $end
$var wire 1 M Cout $end
$upscope $end
$scope module bit1 $end
$var wire 1 N A $end
$var wire 1 O B $end
$var wire 1 M C $end
$var wire 1 P Y $end
$var wire 1 Q Cout $end
$upscope $end
$scope module bit2 $end
$var wire 1 R A $end
$var wire 1 S B $end
$var wire 1 Q C $end
$var wire 1 T Y $end
$var wire 1 U Cout $end
$upscope $end
$scope module msb $end
$var wire 1 V A $end
$var wire 1 W B $end
$var wire 1 U C $end
$var wire 1 X Y $end
$var wire 1 Y Cout $end
$upscope $end
$upscope $end
$scope module Aplus $end
$var wire 4 A A [3:0] $end
$var wire 4 B B [7:4] $end
$var wire 4 / Y [3:0] $end
$var wire 4 Z second_carry [3:0] $end
$scope module lsb $end
$var wire 1 [ A $end
$var wire 1 \ B $end
$var wire 1 ] C $end
$var wire 1 ^ Y $end
$var wire 1 _ Cout $end
$upscope $end
$scope module bit1 $end
$var wire 1 ` A $end
$var wire 1 a B $end
$var wire 1 _ C $end
$var wire 1 b Y $end
$var wire 1 c Cout $end
$upscope $end
$scope module bit2 $end
$var wire 1 d A $end
$var wire 1 e B $end
$var wire 1 c C $end
$var wire 1 f Y $end
$var wire 1 g Cout $end
$upscope $end
$scope module msb $end
$var wire 1 h A $end
$var wire 1 i B $end
$var wire 1 g C $end
$var wire 1 j Y $end
$var wire 1 k Cout $end
$upscope $end
$upscope $end
$scope module Aminus $end
$var wire 4 A A [3:0] $end
$var wire 4 E B [3:0] $end
$var wire 4 0 Y [3:0] $end
$var wire 4 l second_carry [3:0] $end
$scope module lsb $end
$var wire 1 [ A $end
$var wire 1 L B $end
$var wire 1 m C $end
$var wire 1 n Y $end
$var wire 1 o Cout $end
$upscope $end
$scope module bit1 $end
$var wire 1 ` A $end
$var wire 1 P B $end
$var wire 1 o C $end
$var wire 1 p Y $end
$var wire 1 q Cout $end
$upscope $end
$scope module bit2 $end
$var wire 1 d A $end
$var wire 1 T B $end
$var wire 1 q C $end
$var wire 1 r Y $end
$var wire 1 s Cout $end
$upscope $end
$scope module msb $end
$var wire 1 h A $end
$var wire 1 X B $end
$var wire 1 s C $end
$var wire 1 t Y $end
$var wire 1 u Cout $end
$upscope $end
$upscope $end
$upscope $end
$upscope $end
$scope task advance_clock $end
$upscope $end
$scope function seg_encode $end
$upscope $end
$scope task test_segs $end
$upscope $end
$upscope $end
$enddefinitions $end

#0
$dumpvars
bx !
bx "
0#
1$
bx %
bx &
b1110 '
bx (
bx )
bx *
bx +
0,
1-
0.
bx /
bx 0
bz1 1
bz0 2
03
14
05
b0 6
b11 7
b1110 8
19
0:
1;
0<
1=
0>
1?
0@
bx A
bx B
bx C
bx D
bx E
bx F
b1 G
bx H
xI
1J
0K
xL
xM
xN
0O
xP
xQ
xR
0S
xT
xU
xV
0W
xX
xY
bx Z
x[
x\
0]
x^
x_
x`
xa
xb
xc
xd
xe
xf
xg
xh
xi
xj
xk
bx l
0m
xn
xo
xp
xq
xr
xs
xt
xu
$end

#5000
b0 !
b0 "
0$
b0 %
b0 &
b1000000 (
b0 )
b0 *
b0 +
0-
b0 /
b0 0
b0 A
b0 B
b1000000 C
b0 D
b0 E
b1111 F
b1111 H
1I
0L
1M
1N
0P
1Q
1R
0T
1U
1V
0X
1Y
b0 Z
0[
0\
0^
0_
0`
0a
0b
0c
0d
0e
0f
0g
0h
0i
0j
0k
b0 l
0n
0o
0p
0q
0r
0s
0t
0u

#7000
1#
b1101 '
1,
1.
bz0 1
bz1 2
04
15
b1 6
b0 7
b1101 8
0;
1<
1>
0?
1@

#8000
0#
0,

#9000
1#
1,
0.
bz1 1
bz0 2
14
05

#10000
0#
0,

#11000
1#
b1011 '
1,
1.
bz0 1
bz1 2
04
15
b10 6
b1 7
b1011 8
1:
0>
1?
0@

#12000
0#
0,

#13000
1#
1,
0.
bz1 1
bz0 2
14
05

#14000
0#
0,

#15000
1#
b111 '
1,
1.
bz0 1
bz1 2
04
15
b11 6
b10 7
b111 8
1;
0<
1>
0?
1@

#16000
0#
0,

#17000
1#
1,
0.
bz1 1
bz0 2
14
05

#18000
0#
0,

#19000
1#
b1110 '
1,
1.
bz0 1
bz1 2
04
15
b0 6
b11 7
b1110 8
0:
0>
1?
0@

#20000
0#
0,

#21000
1#
1,
0.
bz1 1
bz0 2
14
05

#22000
b1 "
0#
b1111 %
b1 &
b10000 )
b1 +
0,
b1 /
b1111 0
b0 A
b1 B
b1111 E
b1110 F
b0 H
0I
1L
0M
1N
1P
0Q
1R
1T
0U
1V
1X
0Y
0[
1\
1^
0`
0a
0d
0e
0h
0i
1n
1p
1r
1t

#24000
1#
b1101 '
b1111001 (
1,
1.
bz0 1
bz1 2
04
15
b1 6
b0 7
b1101 8
0;
1<
1>
0?
1@
b1111001 C
b1 D

#25000
0#
0,

#26000
1#
1,
0.
bz1 1
bz0 2
14
05

#27000
0#
0,

#28000
1#
b1011 '
1,
1.
bz0 1
bz1 2
04
15
b10 6
b1 7
b1011 8
1:
0>
1?
0@

#29000
0#
0,

#30000
1#
1,
0.
bz1 1
bz0 2
14
05

#31000
0#
0,

#32000
1#
b111 '
b1110 (
1,
1.
bz0 1
bz1 2
04
15
b11 6
b10 7
b111 8
1;
0<
1>
0?
1@
b1110 C
b1111 D

#33000
0#
0,

#34000
1#
1,
0.
bz1 1
bz0 2
14
05

#35000
0#
0,

#36000
1#
b1110 '
b1000000 (
1,
1.
bz0 1
bz1 2
04
15
b0 6
b11 7
b1110 8
0:
0>
1?
0@
b1000000 C
b0 D

#37000
0#
0,

#38000
1#
1,
0.
bz1 1
bz0 2
14
05

#39000
b10 "
0#
b1110 %
b10 &
b100000 )
b10 +
0,
b10 /
b1110 0
b0 A
b10 B
b1110 E
b1101 F
b1 H
1I
0L
1M
0N
1R
1V
0[
0\
0^
0`
1a
1b
0d
0e
0h
0i
0n

#41000
1#
b1101 '
b100100 (
1,
1.
bz0 1
bz1 2
04
15
b1 6
b0 7
b1101 8
0;
1<
1>
0?
1@
b100100 C
b10 D

#42000
0#
0,

#43000
1#
1,
0.
bz1 1
bz0 2
14
05

#44000
0#
0,

#45000
1#
b1011 '
1,
1.
bz0 1
bz1 2
04
15
b10 6
b1 7
b1011 8
1:
0>
1?
0@

#46000
0#
0,

#47000
1#
1,
0.
bz1 1
bz0 2
14
05

#48000
0#
0,

#49000
1#
b111 '
b110 (
1,
1.
bz0 1
bz1 2
04
15
b11 6
b10 7
b111 8
1;
0<
1>
0?
1@
b110 C
b1110 D

#50000
0#
0,

#51000
1#
1,
0.
bz1 1
bz0 2
14
05

#52000
0#
0,

#53000
1#
b1110 '
b1000000 (
1,
1.
bz0 1
bz1 2
04
15
b0 6
b11 7
b1110 8
0:
0>
1?
0@
b1000000 C
b0 D

#54000
0#
0,

#55000
1#
1,
0.
bz1 1
bz0 2
14
05

#56000
b11 "
0#
b1101 %
b11 &
b110000 )
b11 +
0,
b11 /
b1101 0
b0 A
b11 B
b1101 E
b1100 F
b0 H
0I
1L
0M
0N
0P
1R
1V
0[
1\
1^
0`
1a
0d
0e
0h
0i
1n
0p

#58000
1#
b1101 '
b110000 (
1,
1.
bz0 1
bz1 2
04
15
b1 6
b0 7
b1101 8
0;
1<
1>
0?
1@
b110000 C
b11 D

#59000
0#
0,

#60000
1#
1,
0.
bz1 1
bz0 2
14
05

#61000
0#
0,

#62000
1#
b1011 '
1,
1.
bz0 1
bz1 2
04
15
b10 6
b1 7
b1011 8
1:
0>
1?
0@

#63000
0#
0,

#64000
1#
1,
0.
bz1 1
bz0 2
14
05

#65000
0#
0,

#66000
1#
b111 '
b100001 (
1,
1.
bz0 1
bz1 2
04
15
b11 6
b10 7
b111 8
1;
0<
1>
0?
1@
b100001 C
b1101 D

#67000
0#
0,

#68000
1#
1,
0.
bz1 1
bz0 2
14
05

#69000
0#
0,

#70000
1#
b1110 '
b1000000 (
1,
1.
bz0 1
bz1 2
04
15
b0 6
b11 7
b1110 8
0:
0>
1?
0@
b1000000 C
b0 D

#71000
0#
0,

#72000
1#
1,
0.
bz1 1
bz0 2
14
05

#73000
b100 "
0#
b1100 %
b100 &
b1000000 )
b100 +
0,
b100 /
b1100 0
b0 A
b100 B
b1100 E
b1011 F
b11 H
1I
0L
1M
1N
1Q
0R
1V
0[
0\
0^
0`
0a
0b
0d
1e
1f
0h
0i
0n

#75000
1#
b1101 '
b11001 (
1,
1.
bz0 1
bz1 2
04
15
b1 6
b0 7
b1101 8
0;
1<
1>
0?
1@
b11001 C
b100 D

#76000
0#
0,

#77000
1#
1,
0.
bz1 1
bz0 2
14
05

#78000
0#
0,

#79000
1#
b1011 '
1,
1.
bz0 1
bz1 2
04
15
b10 6
b1 7
b1011 8
1:
0>
1?
0@

#80000
0#
0,

#81000
1#
1,
0.
bz1 1
bz0 2
14
05

#82000
0#
0,

#83000
1#
b111 '
b1000110 (
1,
1.
bz0 1
bz1 2
04
15
b11 6
b10 7
b111 8
1;
0<
1>
0?
1@
b1000110 C
b1100 D

#84000
0#
0,

#85000
1#
1,
0.
bz1 1
bz0 2
14
05

#86000
0#
0,

#87000
1#
b1110 '
b1000000 (
1,
1.
bz0 1
bz1 2
04
15
b0 6
b11 7
b1110 8
0:
0>
1?
0@
b1000000 C
b0 D

#88000
0#
0,

#89000
1#
1,
0.
bz1 1
bz0 2
14
05

#90000
b101 "
0#
b1011 %
b101 &
b1010000 )
b101 +
0,
b101 /
b1011 0
b0 A
b101 B
b1011 E
b1010 F
b0 H
0I
1L
0M
1N
1P
0Q
0R
0T
1V
0[
1\
1^
0`
0a
0d
1e
0h
0i
1n
1p
0r

#92000
1#
b1101 '
b10010 (
1,
1.
bz0 1
bz1 2
04
15
b1 6
b0 7
b1101 8
0;
1<
1>
0?
1@
b10010 C
b101 D

#93000
0#
0,

#94000
1#
1,
0.
bz1 1
bz0 2
14
05

#95000
0#
0,

#96000
1#
b1011 '
1,
1.
bz0 1
bz1 2
04
15
b10 6
b1 7
b1011 8
1:
0>
1?
0@

#97000
0#
0,

#98000
1#
1,
0.
bz1 1
bz0 2
14
05

#99000
0#
0,

#100000
1#
b111 '
b11 (
1,
1.
bz0 1
bz1 2
04
15
b11 6
b10 7
b111 8
1;
0<
1>
0?
1@
b11 C
b1011 D

#101000
0#
0,

#102000
1#
1,
0.
bz1 1
bz0 2
14
05

#103000
0#
0,

#104000
1#
b1110 '
b1000000 (
1,
1.
bz0 1
bz1 2
04
15
b0 6
b11 7
b1110 8
0:
0>
1?
0@
b1000000 C
b0 D

#105000
0#
0,

#106000
1#
1,
0.
bz1 1
bz0 2
14
05

#107000
b110 "
0#
b1010 %
b110 &
b1100000 )
b110 +
0,
b110 /
b1010 0
b0 A
b110 B
b1010 E
b1001 F
b1 H
1I
0L
1M
0N
0R
1V
0[
0\
0^
0`
1a
1b
0d
1e
0h
0i
0n

#109000
1#
b1101 '
b10 (
1,
1.
bz0 1
bz1 2
04
15
b1 6
b0 7
b1101 8
0;
1<
1>
0?
1@
b10 C
b110 D

#110000
0#
0,

#111000
1#
1,
0.
bz1 1
bz0 2
14
05

#112000
0#
0,

#113000
1#
b1011 '
1,
1.
bz0 1
bz1 2
04
15
b10 6
b1 7
b1011 8
1:
0>
1?
0@

#114000
0#
0,

#115000
1#
1,
0.
bz1 1
bz0 2
14
05

#116000
0#
0,

#117000
1#
b111 '
b1000 (
1,
1.
bz0 1
bz1 2
04
15
b11 6
b10 7
b111 8
1;
0<
1>
0?
1@
b1000 C
b1010 D

#118000
0#
0,

#119000
1#
1,
0.
bz1 1
bz0 2
14
05

#120000
0#
0,

#121000
1#
b1110 '
b1000000 (
1,
1.
bz0 1
bz1 2
04
15
b0 6
b11 7
b1110 8
0:
0>
1?
0@
b1000000 C
b0 D

#122000
0#
0,

#123000
1#
1,
0.
bz1 1
bz0 2
14
05

#124000
b111 "
0#
b1001 %
b111 &
b1110000 )
b111 +
0,
b111 /
b1001 0
b0 A
b111 B
b1001 E
b1000 F
b0 H
0I
1L
0M
0N
0P
0R
1V
0[
1\
1^
0`
1a
0d
1e
0h
0i
1n
0p

#126000
1#
b1101 '
b1111000 (
1,
1.
bz0 1
bz1 2
04
15
b1 6
b0 7
b1101 8
0;
1<
1>
0?
1@
b1111000 C
b111 D

#127000
0#
0,

#128000
1#
1,
0.
bz1 1
bz0 2
14
05

#129000
0#
0,

#130000
1#
b1011 '
1,
1.
bz0 1
bz1 2
04
15
b10 6
b1 7
b1011 8
1:
0>
1?
0@

#131000
0#
0,

#132000
1#
1,
0.
bz1 1
bz0 2
14
05

#133000
0#
0,

#134000
1#
b111 '
b10000 (
1,
1.
bz0 1
bz1 2
04
15
b11 6
b10 7
b111 8
1;
0<
1>
0?
1@
b10000 C
b1001 D

#135000
0#
0,

#136000
1#
1,
0.
bz1 1
bz0 2
14
05

#137000
0#
0,

#138000
1#
b1110 '
b1000000 (
1,
1.
bz0 1
bz1 2
04
15
b0 6
b11 7
b1110 8
0:
0>
1?
0@
b1000000 C
b0 D

#139000
0#
0,

#140000
1#
1,
0.
bz1 1
bz0 2
14
05

#141000
b1000 "
0#
b1000 %
b1000 &
b10000000 )
b1000 +
0,
b1000 /
b1000 0
b0 A
b1000 B
b1000 E
b111 F
b111 H
1I
0L
1M
1N
1Q
1R
1U
0V
0[
0\
0^
0`
0a
0b
0d
0e
0f
0h
1i
1j
0n

#143000
1#
b1101 '
b0 (
1,
1.
bz0 1
bz1 2
04
15
b1 6
b0 7
b1101 8
0;
1<
1>
0?
1@
b0 C
b1000 D

#144000
0#
0,

#145000
1#
1,
0.
bz1 1
bz0 2
14
05

#146000
0#
0,

#147000
1#
b1011 '
1,
1.
bz0 1
bz1 2
04
15
b10 6
b1 7
b1011 8
1:
0>
1?
0@

#148000
0#
0,

#149000
1#
1,
0.
bz1 1
bz0 2
14
05

#150000
0#
0,

#151000
1#
b111 '
1,
1.
bz0 1
bz1 2
04
15
b11 6
b10 7
b111 8
1;
0<
1>
0?
1@

#152000
0#
0,

#153000
1#
1,
0.
bz1 1
bz0 2
14
05

#154000
0#
0,

#155000
1#
b1110 '
b1000000 (
1,
1.
bz0 1
bz1 2
04
15
b0 6
b11 7
b1110 8
0:
0>
1?
0@
b1000000 C
b0 D

#156000
0#
0,

#157000
1#
1,
0.
bz1 1
bz0 2
14
05

#158000
b1001 "
0#
b111 %
b1001 &
b10010000 )
b1001 +
0,
b1001 /
b111 0
b0 A
b1001 B
b111 E
b110 F
b0 H
0I
1L
0M
1N
1P
0Q
1R
1T
0U
0V
0X
0[
1\
1^
0`
0a
0d
0e
0h
1i
1n
1p
1r
0t

#160000
1#
b1101 '
b10000 (
1,
1.
bz0 1
bz1 2
04
15
b1 6
b0 7
b1101 8
0;
1<
1>
0?
1@
b10000 C
b1001 D

#161000
0#
0,

#162000
1#
1,
0.
bz1 1
bz0 2
14
05

#163000
0#
0,

#164000
1#
b1011 '
1,
1.
bz0 1
bz1 2
04
15
b10 6
b1 7
b1011 8
1:
0>
1?
0@

#165000
0#
0,

#166000
1#
1,
0.
bz1 1
bz0 2
14
05

#167000
0#
0,

#168000
1#
b111 '
b1111000 (
1,
1.
bz0 1
bz1 2
04
15
b11 6
b10 7
b111 8
1;
0<
1>
0?
1@
b1111000 C
b111 D

#169000
0#
0,

#170000
1#
1,
0.
bz1 1
bz0 2
14
05

#171000
0#
0,

#172000
1#
b1110 '
b1000000 (
1,
1.
bz0 1
bz1 2
04
15
b0 6
b11 7
b1110 8
0:
0>
1?
0@
b1000000 C
b0 D

#173000
0#
0,

#174000
1#
1,
0.
bz1 1
bz0 2
14
05

#175000
b1010 "
0#
b110 %
b1010 &
b10100000 )
b1010 +
0,
b1010 /
b110 0
b0 A
b1010 B
b110 E
b101 F
b1 H
1I
0L
1M
0N
1R
0V
0[
0\
0^
0`
1a
1b
0d
0e
0h
1i
0n

#177000
1#
b1101 '
b1000 (
1,
1.
bz0 1
bz1 2
04
15
b1 6
b0 7
b1101 8
0;
1<
1>
0?
1@
b1000 C
b1010 D

#178000
0#
0,

#179000
1#
1,
0.
bz1 1
bz0 2
14
05

#180000
0#
0,

#181000
1#
b1011 '
1,
1.
bz0 1
bz1 2
04
15
b10 6
b1 7
b1011 8
1:
0>
1?
0@

#182000
0#
0,

#183000
1#
1,
0.
bz1 1
bz0 2
14
05

#184000
0#
0,

#185000
1#
b111 '
b10 (
1,
1.
bz0 1
bz1 2
04
15
b11 6
b10 7
b111 8
1;
0<
1>
0?
1@
b10 C
b110 D

#186000
0#
0,

#187000
1#
1,
0.
bz1 1
bz0 2
14
05

#188000
0#
0,

#189000
1#
b1110 '
b1000000 (
1,
1.
bz0 1
bz1 2
04
15
b0 6
b11 7
b1110 8
0:
0>
1?
0@
b1000000 C
b0 D

#190000
0#
0,

#191000
1#
1,
0.
bz1 1
bz0 2
14
05

#192000
b1011 "
0#
b101 %
b1011 &
b10110000 )
b1011 +
0,
b1011 /
b101 0
b0 A
b1011 B
b101 E
b100 F
b0 H
0I
1L
0M
0N
0P
1R
0V
0[
1\
1^
0`
1a
0d
0e
0h
1i
1n
0p

#194000
1#
b1101 '
b11 (
1,
1.
bz0 1
bz1 2
04
15
b1 6
b0 7
b1101 8
0;
1<
1>
0?
1@
b11 C
b1011 D

#195000
0#
0,

#196000
1#
1,
0.
bz1 1
bz0 2
14
05

#197000
0#
0,

